bimmer_connected/__init__.py
bimmer_connected/account.py
bimmer_connected/cli.py
bimmer_connected/const.py
bimmer_connected/coord_convert.py
bimmer_connected/models.py
bimmer_connected/py.typed
bimmer_connected/utils.py
bimmer_connected/api/__init__.py
bimmer_connected/api/authentication.py
bimmer_connected/api/client.py
bimmer_connected/api/regions.py
bimmer_connected/api/utils.py
bimmer_connected/tests/__init__.py
bimmer_connected/tests/common.py
bimmer_connected/tests/conftest.py
bimmer_connected/tests/test_account.py
bimmer_connected/tests/test_api.py
bimmer_connected/tests/test_cli.py
bimmer_connected/tests/test_remote_services.py
bimmer_connected/tests/test_utils.py
bimmer_connected/tests/test_vehicle.py
bimmer_connected/tests/test_vehicle_status.py
bimmer_connected/tests/responses/bmw-eadrax-vcs_v5_vehicle-list.json
bimmer_connected/tests/responses/mini-eadrax-vcs_v5_vehicle-list.json
bimmer_connected/tests/responses/toyota-eadrax-vcs_v5_vehicle-list.json
bimmer_connected/tests/responses/F31/bmw-eadrax-vcs_v4_vehicles_state_WBA00000000000F31.json
bimmer_connected/tests/responses/F31/bmw-eadrax-vcs_v5_vehicle-data_profile_WBA00000000000F31.json
bimmer_connected/tests/responses/F31/bmw-eadrax-vcs_v5_vehicle-list.json
bimmer_connected/tests/responses/G01/bmw-eadrax-crccs_v2_vehicles_WBA00000000DEMO04.json
bimmer_connected/tests/responses/G01/bmw-eadrax-vcs_v4_vehicles_state_WBA00000000DEMO04.json
bimmer_connected/tests/responses/G01/bmw-eadrax-vcs_v5_vehicle-data_profile_WBA00000000DEMO04.json
bimmer_connected/tests/responses/G01/bmw-eadrax-vcs_v5_vehicle-list.json
bimmer_connected/tests/responses/G20/bmw-eadrax-vcs_v4_vehicles_state_WBA00000000DEMO03.json
bimmer_connected/tests/responses/G20/bmw-eadrax-vcs_v5_vehicle-data_profile_WBA00000000DEMO03.json
bimmer_connected/tests/responses/G20/bmw-eadrax-vcs_v5_vehicle-list.json
bimmer_connected/tests/responses/G26/bmw-eadrax-crccs_v2_vehicles_WBA00000000DEMO02.json
bimmer_connected-0.17.3.dist-info/licenses/LICENSE
bimmer_connected-0.17.3.dist-info/METADATA
bimmer_connected-0.17.3.dist-info/WHEEL
bimmer_connected-0.17.3.dist-info/entry_points.txt
bimmer_connected-0.17.3.dist-info/pbr.json
bimmer_connected-0.17.3.dist-info/top_level.txt
bimmer_connected-0.17.3.dist-info/RECORD
