Metadata-Version: 2.4
Name: bimmer_connected
Version: 0.17.3
Summary: Library to read data from the BMW Connected Drive portal
Home-page: https://github.com/bimmerconnected/bimmer_connected
Author: gerard33, rikroe
License: Apache-2.0
Project-URL: Bug Tracker, https://github.com/bimmerconnected/bimmer_connected/issues
Project-URL: Documentation, https://bimmer-connected.readthedocs.io/en/latest/
Project-URL: Source Code, https://github.com/bimmerconnected/bimmer_connected
Keywords: BMW,Connected Drive,home automation
Classifier: Development Status :: 4 - Beta
Classifier: Environment :: Console
Classifier: Intended Audience :: Developers
Classifier: Programming Language :: Python :: 3
Classifier: Programming Language :: Python :: 3.8
Classifier: Programming Language :: Python :: 3.9
Classifier: Programming Language :: Python :: 3.10
Classifier: Programming Language :: Python :: 3.11
Classifier: Programming Language :: Python :: 3.12
Classifier: Programming Language :: Python :: 3.13
Requires-Python: >= 3.8
License-File: LICENSE
Requires-Dist: httpx
Requires-Dist: pycryptodome>=3.4
Requires-Dist: pyjwt>=2.1.0
Requires-Dist: Pillow
Provides-Extra: china
Requires-Dist: Pillow; extra == "china"
Dynamic: author
Dynamic: classifier
Dynamic: description
Dynamic: description-content-type
Dynamic: home-page
Dynamic: keywords
Dynamic: license
Dynamic: license-file
Dynamic: project-url
Dynamic: requires-dist
Dynamic: requires-python
Dynamic: summary
